Workbook

Sheet Catalogo
A1: Categoria | B1: Documento / template | C1: Órgão ou fonte | D1: Tipo de evidência | E1: Formato / acesso | F1: Prioridade OCRSD | G1: Link da fonte | H1: Observações / limitações
A2: Registro civil | B2: Certidão de nascimento | C2: CNJ / cartórios RCPN | D2: Modelo visual em anexo | E2: PDF oficial com imagens | F2: Alta | G2: https://www.stj.jus.br/internet_docs/biblioteca/clippinglegislacao/Provimento_182_2024_CNJ.pdf | H2: Anexos IV–VII; óbito e natimorto compartilham modelo; inteiro teor é genérico.
A3: Registro civil | B3: Certidão de casamento | C3: CNJ / cartórios RCPN | D3: Modelo visual em anexo | E3: PDF oficial com imagens | F3: Alta | G3: https://www.stj.jus.br/internet_docs/biblioteca/clippinglegislacao/Provimento_182_2024_CNJ.pdf | H3: Anexos IV–VII; óbito e natimorto compartilham modelo; inteiro teor é genérico.
A4: Registro civil | B4: Certidão de óbito | C4: CNJ / cartórios RCPN | D4: Modelo visual em anexo | E4: PDF oficial com imagens | F4: Alta | G4: https://www.stj.jus.br/internet_docs/biblioteca/clippinglegislacao/Provimento_182_2024_CNJ.pdf | H4: Anexos IV–VII; óbito e natimorto compartilham modelo; inteiro teor é genérico.
A5: Registro civil | B5: Certidão de natimorto | C5: CNJ / cartórios RCPN | D5: Modelo visual em anexo | E5: PDF oficial com imagens | F5: Alta | G5: https://www.stj.jus.br/internet_docs/biblioteca/clippinglegislacao/Provimento_182_2024_CNJ.pdf | H5: Anexos IV–VII; óbito e natimorto compartilham modelo; inteiro teor é genérico.
A6: Registro civil | B6: Certidão em inteiro teor | C6: CNJ / cartórios RCPN | D6: Modelo visual em anexo | E6: PDF oficial com imagens | F6: Alta | G6: https://www.stj.jus.br/internet_docs/biblioteca/clippinglegislacao/Provimento_182_2024_CNJ.pdf | H6: Anexos IV–VII; óbito e natimorto compartilham modelo; inteiro teor é genérico.
A7: Registro civil | B7: Declaração de Nascido Vivo (DNV) | C7: Ministério da Saúde | D7: Modelo impresso em manual | E7: PDF com formulário | F7: Alta | G7: https://bvsms.saude.gov.br/bvs/publicacoes/declaracao_nascido_vivo_manual_4ed.pdf | H7: Consultar apêndices; distinguir a versão epidemiológica.
A8: Registro civil | B8: Declaração de Nascido Vivo epidemiológica | C8: Ministério da Saúde | D8: Modelo impresso em manual | E8: PDF com formulário | F8: Alta | G8: https://bvsms.saude.gov.br/bvs/publicacoes/declaracao_nascido_vivo_manual_4ed.pdf | H8: Consultar apêndices; distinguir a versão epidemiológica.
A9: Registro civil | B9: Declaração de Óbito (DO) | C9: Ministério da Saúde | D9: Modelo impresso em manual | E9: PDF com formulário | F9: Alta | G9: https://bvsms.saude.gov.br/bvs/publicacoes/declaracao_obito_manual_preenchimento.pdf | H9: Versão epidemiológica não tem mesma função jurídica.
A10: Registro civil | B10: Declaração de Óbito epidemiológica | C10: Ministério da Saúde | D10: Modelo impresso em manual | E10: PDF com formulário | F10: Alta | G10: https://bvsms.saude.gov.br/bvs/publicacoes/declaracao_obito_manual_preenchimento.pdf | H10: Versão epidemiológica não tem mesma função jurídica.
A11: Identificação | B11: Carteira de Identidade Nacional (CIN) - física | C11: Ministério da Gestão / Detran-RJ | D11: Exemplo visual em portal | E11: Página com imagem | F11: Alta | G11: https://www.detran.rj.gov.br/todos-os-servicos/servicos-dic/carteira-de-identidade-nacional-cin.html | H11: Campos e fontes também na especificação federal: https://www.gov.br/participamaisbrasil/mi-cin
A12: Identificação | B12: Carteira de Identidade Nacional (CIN) - digital | C12: Ministério da Gestão / Detran-RJ | D12: Exemplo visual em portal | E12: Página com imagem | F12: Alta | G12: https://www.detran.rj.gov.br/todos-os-servicos/servicos-dic/carteira-de-identidade-nacional-cin.html | H12: Campos e fontes também na especificação federal: https://www.gov.br/participamaisbrasil/mi-cin
... A211: Fiscal / eletrônicos | B211: Layout SEFIN/ADN NFS-e - anexos | C211: Portal Nacional NFS-e | D211: Leiaute / XSD oficial | E211: Manuais e esquemas XSD | F211: Média | G211: https://www.gov.br/nfse/pt-br/biblioteca/documentacao-tecnica/documentacao-atual | H211: Modelo estrutural não equivale ao PDF final de cada município.

Sheet Fontes
A1: Órgão / acervo | B1: Registros vinculados | C1: Categorias | D1: Tipo / origem | E1: URL pública
A2: INSS | B2: 32 | C2: INSS / previdência | D2: Modelo/formulário no acervo | E2: https://www.gov.br/inss/pt-br/centrais-de-conteudo/formularios/formularios
A3: Itamaraty / consulado | B3: 23 | C3: Cartórios / procurações | D3: Modelo textual publicado | E3: https://www.gov.br/mre/pt-br/consulado-bruxelas/procuracoes/procuracao-publica
A4: Receita Federal | B4: 23 | C4: Receita / tributário | D4: Modelo no acervo oficial | E4: https://www.gov.br/receitafederal/pt-br/centrais-de-conteudo/formularios/modelos
A5: eSocial / Ministério do Trabalho | B5: 15 | C5: Trabalho / eSocial | D5: Modelo editável publicado | E5: https://www.gov.br/esocial/pt-br/empregador-domestico/manual-do-empregador-domestico
A6: AGU / Compras.gov.br | B6: 12 | C6: Administração / licitações | D6: Modelo padronizado editável | E6: https://www.gov.br/agu/pt-br/composicao/cgu/cgu/modelos/licitacoesecontratos/14133/pregao-e-concorrencia
A7: Ministério da Defesa | B7: 8 | C7: Documentos militares | D7: Modelo padronizado em anexo | E7: https://www.gov.br/defesa/pt-br/assuntos/industria-de-defesa/comissao-mista-da-industria-de-defesa-cmid-1/arquivos/e-credenciamentos-de-empresas-de-defesa-ed/7-portaria-no-706-de-13-de-junho-de-2016.pdf
A8: Anvisa | B8: 8 | C8: Saúde / Anvisa | D8: PDF modelo vigente, versão 2 | E8: https://www.gov.br/anvisa/pt-br/assuntos/medicamentos/controlados/sncr/modelos-de-receituarios/modelos-vigentes
A9: Cadastro Único / Caixa | B9: 6 | C9: Assistência social | D9: Formulários em área do sistema | E9: https://www.caixa.gov.br/poder-publico/modernizacao-gestao/cadastro-unico/perguntas-frequentes/Paginas/default.aspx
A10: AGU / Compras.gov.br | B10: 6 | C10: Administração / licitações | D10: Índice de modelos | E10: https://www.gov.br/compras/pt-br/nllc/modelos-de-licitacoes-e-contratos/
A11: Portal Nacional NF-e | B11: 6 | C11: Fiscal / eletrônicos | D11: Leiaute / manual oficial | E11: https://www.nfe.fazenda.gov.br/portal/listaConteudo.aspx?AspxAutoDetectCookieSupport=1&tipoConteudo=ndIjl+iEFdE%3D
A12: CNJ / cartórios RCPN | B12: 5 | C12: Registro civil | D12: Modelo visual em anexo | E12: https://www.stj.jus.br/internet_docs/biblioteca/clippinglegislacao/Provimento_182_2024_CNJ.pdf
A13: Vigilância Epidemiológica Jundiaí | B13: 5 | C13: Saúde | D13: Formulários em portal público | E13: https://jundiai.sp.gov.br/saude/vigilancia-epidemiologica/formularios/
... A41: Senatran | B41: 1 | C41: Trânsito / veículos | D41: Emissão autenticada (sem blank público) | E41: https://www.gov.br/pt-br/servicos/emitir-o-certificado-de-registro-e-licenciamento-de-veiculo-digital-crlv-e

Sheet Resumo
A1: Catálogo de documentos brasileiros — OCRSD
A4: Registros catalogados | C4: =COUNTA(Catalogo!B2:B500) -> 210 | D4: Fontes distintas | F4: 40
A6: Categoria | B6: Total | C6: Alta prioridade
A7: Administração / licitações | B7: =COUNTIF(Catalogo!$A$2:$A$500,A7) -> 23 | C7: =COUNTIFS(Catalogo!$A$2:$A$500,A7,Catalogo!$F$2:$F$500,"Alta") -> 0
A8: Agropecuária | B8: =COUNTIF(Catalogo!$A$2:$A$500,A8) -> 4 | C8: =COUNTIFS(Catalogo!$A$2:$A$500,A8,Catalogo!$F$2:$F$500,"Alta") -> 0
A9: Assistência social | B9: =COUNTIF(Catalogo!$A$2:$A$500,A9) -> 7 | C9: =COUNTIFS(Catalogo!$A$2:$A$500,A9,Catalogo!$F$2:$F$500,"Alta") -> 1
A10: Cartórios / procurações | B10: =COUNTIF(Catalogo!$A$2:$A$500,A10) -> 24 | C10: =COUNTIFS(Catalogo!$A$2:$A$500,A10,Catalogo!$F$2:$F$500,"Alta") -> 24
A11: Documentos militares | B11: =COUNTIF(Catalogo!$A$2:$A$500,A11) -> 8 | C11: =COUNTIFS(Catalogo!$A$2:$A$500,A11,Catalogo!$F$2:$F$500,"Alta") -> 0
A12: Educação | B12: =COUNTIF(Catalogo!$A$2:$A$500,A12) -> 4 | C12: =COUNTIFS(Catalogo!$A$2:$A$500,A12,Catalogo!$F$2:$F$500,"Alta") -> 0
A13: Empresas / Junta Comercial | B13: =COUNTIF(Catalogo!$A$2:$A$500,A13) -> 9 | C13: =COUNTIFS(Catalogo!$A$2:$A$500,A13,Catalogo!$F$2:$F$500,"Alta") -> 3
A14: Fiscal / eletrônicos | B14: =COUNTIF(Catalogo!$A$2:$A$500,A14) -> 10 | C14: =COUNTIFS(Catalogo!$A$2:$A$500,A14,Catalogo!$F$2:$F$500,"Alta") -> 0
A15: INSS / previdência | B15: =COUNTIF(Catalogo!$A$2:$A$500,A15) -> 32 | C15: =COUNTIFS(Catalogo!$A$2:$A$500,A15,Catalogo!$F$2:$F$500,"Alta") -> 0
A16: Identificação | B16: =COUNTIF(Catalogo!$A$2:$A$500,A16) -> 13 | C16: =COUNTIFS(Catalogo!$A$2:$A$500,A16,Catalogo!$F$2:$F$500,"Alta") -> 5
A17: Receita / tributário | B17: =COUNTIF(Catalogo!$A$2:$A$500,A17) -> 27 | C17: =COUNTIFS(Catalogo!$A$2:$A$500,A17,Catalogo!$F$2:$F$500,"Alta") -> 4
A18: Registro civil | B18: =COUNTIF(Catalogo!$A$2:$A$500,A18) -> 9 | C18: =COUNTIFS(Catalogo!$A$2:$A$500,A18,Catalogo!$F$2:$F$500,"Alta") -> 9
... A22: Trânsito / veículos | B22: =COUNTIF(Catalogo!$A$2:$A$500,A22) -> 4 | C22: =COUNTIFS(Catalogo!$A$2:$A$500,A22,Catalogo!$F$2:$F$500,"Alta") -> 0
A26: Como usar a planilha
A28: 1. A lista reúne tipos de documento e variações com fontes públicas. Não são 210 PDFs prontos para imprimir.
A29: 2. Tipo de evidência = existência de modelo visual, formulário editável, esquema de campos ou referência legal.
A30: 3. Para OCR, priorize a estrutura e variabilidade visual. Versões históricas devem ser rotuladas.
A31: 4. Use somente dados sintéticos; evite QR codes de validação real, números reais e elementos que possam conferir autenticidade.
A32: 5. Verifique atualizações normativas, licenças e marcas antes da reprodução em uma base pública.
